{
  "showSlug": "pride-and-prejudice",
  "episodes": [
    {
      "title": "Episode 1",
      "episodeNumber": 1,
      "seasonNumber": 1,
      "description": "Episode 1",
      "duration": 45,
      "videoUrl": "https://drive.google.com/file/d/1IhnmD3L076SzW7vYAFJ0vr3_FdFrBFkG/preview"
    },
    {
      "title": "Episode 2",
      "episodeNumber": 2,
      "seasonNumber": 1,
      "description": "Episode 2",
      "duration": 45,
      "videoUrl": "https://drive.google.com/file/d/1CaihndD278xfKlrIYi9gcVrNaZVzjG6q/preview"
    },
    {
      "title": "Episode 3",
      "episodeNumber": 3,
      "seasonNumber": 1,
      "description": "Episode 3",
      "duration": 45,
      "videoUrl": "https://drive.google.com/file/d/1o1JteQqdxg8gid4uiwrNVExrFsk1VlGb/preview"
    },
    {
      "title": "Episode 4",
      "episodeNumber": 4,
      "seasonNumber": 1,
      "description": "Episode 4",
      "duration": 45,
      "videoUrl": "https://drive.google.com/file/d/1VvYq1qmr8CzLciHX0lPPwUHwjFj7v2ef/preview"
    },
    {
      "title": "Episode 5",
      "episodeNumber": 5,
      "seasonNumber": 1,
      "description": "Episode 5",
      "duration": 45,
      "videoUrl": "https://drive.google.com/file/d/1j86qIVKLzbQX7O6XbO-wycafazxXSzyy/preview"
    },
    {
      "title": "Episode 6",
      "episodeNumber": 6,
      "seasonNumber": 1,
      "description": "Episode 6",
      "duration": 45,
      "videoUrl": "https://drive.google.com/file/d/1_S3Qy-i7BB9agYTeb47kUn3q7LXvWvn4/preview"
    },
    {
      "title": "Episode 7",
      "episodeNumber": 7,
      "seasonNumber": 1,
      "description": "Episode 7",
      "duration": 45,
      "videoUrl": "https://drive.google.com/file/d/16abBCfCLtkJyt3T90NEzWudy5B7cnSqz/preview"
    },
    {
      "title": "Episode 8",
      "episodeNumber": 8,
      "seasonNumber": 1,
      "description": "Episode 8",
      "duration": 45,
      "videoUrl": "https://drive.google.com/file/d/1NkROQYqJH9KpLUh-s_o6jG5KtSF2p_6l/preview"
    },
    {
      "title": "Episode 9",
      "episodeNumber": 9,
      "seasonNumber": 1,
      "description": "Episode 9",
      "duration": 45,
      "videoUrl": "https://drive.google.com/file/d/1cKPcRs6WQm6uz1MDJ4LVWfcRWTm0Mfwt/preview"
    },
    {
      "title": "Episode 10",
      "episodeNumber": 10,
      "seasonNumber": 1,
      "description": "Episode 10",
      "duration": 45,
      "videoUrl": "https://drive.google.com/file/d/1yHnm4grKcfLDbpFqqsoKo4SmTamEB3Fq/preview"
    },
    {
      "title": "Episode 11",
      "episodeNumber": 11,
      "seasonNumber": 1,
      "description": "Episode 11",
      "duration": 45,
      "videoUrl": "https://drive.google.com/file/d/1hGxurz6zNQ_fLnzMHqAgu-UfmqhPW3Ox/preview"
    },
    {
      "title": "Episode 12",
      "episodeNumber": 12,
      "seasonNumber": 1,
      "description": "Episode 12",
      "duration": 45,
      "videoUrl": "https://drive.google.com/file/d/18mMa7bLDYQqFv2Q0qBQhqPXT7be6O92r/preview"
    },
    {
      "title": "Episode 13",
      "episodeNumber": 13,
      "seasonNumber": 1,
      "description": "Episode 13",
      "duration": 45,
      "videoUrl": "https://drive.google.com/file/d/1juqFk6OrNdPgH5LR3uNriNpa-QHZ0Fv9/preview"
    },
    {
      "title": "Episode 14",
      "episodeNumber": 14,
      "seasonNumber": 1,
      "description": "Episode 14",
      "duration": 45,
      "videoUrl": "https://drive.google.com/file/d/1VyZch1olT3kkJdRI3y1J6A-BzMiO64Id/preview"
    },
    {
      "title": "Episode 15",
      "episodeNumber": 15,
      "seasonNumber": 1,
      "description": "Episode 15",
      "duration": 45,
      "videoUrl": "https://drive.google.com/file/d/15-JJrZXPmNXaVgB_EGlO2Nf1VSHx5wU0/preview"
    },
    {
      "title": "Episode 16",
      "episodeNumber": 16,
      "seasonNumber": 1,
      "description": "Episode 16",
      "duration": 45,
      "videoUrl": "https://drive.google.com/file/d/1u9SPIysxHrf6Sou2tbrd22ivD5g2NRhr/preview"
    },
    {
      "title": "Episode 17",
      "episodeNumber": 17,
      "seasonNumber": 1,
      "description": "Episode 17",
      "duration": 45,
      "videoUrl": "https://drive.google.com/file/d/1MIGjWWd7VdjLRxZSOktOsDOLnDwPCEd0/preview"
    },
    {
      "title": "Episode 18",
      "episodeNumber": 18,
      "seasonNumber": 1,
      "description": "Episode 18",
      "duration": 45,
      "videoUrl": "https://drive.google.com/file/d/1Q0uxkttmWhMjlCWp5O4QsJcZIzCTqGBP/preview"
    },
    {
      "title": "Episode 19",
      "episodeNumber": 19,
      "seasonNumber": 1,
      "description": "Episode 19",
      "duration": 45,
      "videoUrl": "https://drive.google.com/file/d/1n-V1_4-OyiI1RMURX2_Nke4EKViDQSuD/preview"
    },
    {
      "title": "Episode 20",
      "episodeNumber": 20,
      "seasonNumber": 1,
      "description": "Episode 20",
      "duration": 45,
      "videoUrl": "https://drive.google.com/file/d/19cXIZi1Pcwi6cOtiz9z_4DhQaFUSsmJb/preview"
    },
    {
      "title": "Episode 21",
      "episodeNumber": 21,
      "seasonNumber": 1,
      "description": "Episode 21",
      "duration": 45,
      "videoUrl": "https://drive.google.com/file/d/1wNj29ra7gxSVNZ-D0ai-eMiQ3JFywrln/preview"
    }
  ]
}